{
  "last_update": "2026-01-28T18:51:30.220623",
  "articles": [
    {
      "id": "704373dbb7d7",
      "title": "Ethiopia: Allied Gold Sells Kurmuk Project to China's Zijin",
      "summary": "[Reporter] Egyptian firm poised to earn USD 375mln from sale, Ethiopian gov't likely to get nothing",
      "link": "https://allafrica.com/stories/202601280575.html",
      "source": "AllAfrica",
      "category": "Économie",
      "region": "Afrique du Nord",
      "published_at": "2026-01-28T16:59:53",
      "fetched_at": "2026-01-28T18:51:29.553441"
    },
    {
      "id": "4ce11e52850f",
      "title": "Nigeria: NUPRC Courts Global Investors Ahead of 2025 Oil Licensing Round",
      "summary": "[Premium Times] NUPRC said the webinar is designed to provide investment clarity and execution certainty for companies seeking to participate in the licensing round, which will offer 50 oil and gas blocks across frontier, onshore, shallow-water and...",
      "link": "https://allafrica.com/stories/202601280573.html",
      "source": "AllAfrica",
      "category": "Économie",
      "region": "Afrique de l'Ouest",
      "published_at": "2026-01-28T16:58:59",
      "fetched_at": "2026-01-28T18:51:29.553463"
    },
    {
      "id": "4605408dbb0b",
      "title": "Africa: Joint U.S. - African Union Statement on Launch of a Strategic Investment Working Group",
      "summary": "[State Department] Addis Ababa -- The following joint statement was released by the Government of the United States of America and the African Union Commission on the occasion of today's agreement to establish a Strategic Investment Working Group.",
      "link": "https://allafrica.com/stories/202601280555.html",
      "source": "AllAfrica",
      "category": "Économie",
      "region": "Afrique",
      "published_at": "2026-01-28T16:39:12",
      "fetched_at": "2026-01-28T18:51:29.553499"
    },
    {
      "id": "9f117280503b",
      "title": "Afrique: La BAD défend l'économie circulaire comme voie vers une croissance industrielle durable pour le continent",
      "summary": "[Fratmat.info] Dans le cadre de la 7e session de l'Assemblée des Nations unies pour l'environnement (UNEA-7), qui s'est tenue sur le thème «Promouvoir des solutions durables pour une planète résiliente», la Banque africaine de développement a...",
      "link": "https://fr.allafrica.com/stories/202601280540.html",
      "source": "AllAfrica (FR)",
      "category": "Économie",
      "region": "Afrique",
      "published_at": "2026-01-28T16:09:57",
      "fetched_at": "2026-01-28T18:51:29.513748"
    },
    {
      "id": "f1c1270d3883",
      "title": "Afrique: Afreximbank-Fitch - L'APRM plaide pour des notations de crédit plus justes envers le continent",
      "summary": "[Fratmat.info] Le Mécanisme africain d'évaluation par les pairs (APRM) s'est prononcé, le 26 janvier 2026, sur la décision de la Banque africaine d'import-export (Afreximbank) de mettre fin à son accord de notation avec l'agence internationale Fitch...",
      "link": "https://fr.allafrica.com/stories/202601280533.html",
      "source": "AllAfrica (FR)",
      "category": "Économie",
      "region": "Afrique",
      "published_at": "2026-01-28T16:09:54",
      "fetched_at": "2026-01-28T18:51:29.513800"
    },
    {
      "id": "caaf584cf8ca",
      "title": "Kenya: Sun King lance un nouveau système solaire pour les particuliers et les petites entreprises",
      "summary": "[Daba Finance] Sun King a lancé le système solaire domestique HomePlus Max au Kenya, ajoutant un produit de plus grande capacité à sa gamme d'énergie hors réseau.",
      "link": "https://fr.allafrica.com/stories/202601280523.html",
      "source": "AllAfrica (FR)",
      "category": "Économie",
      "region": "Afrique de l'Est",
      "published_at": "2026-01-28T16:02:55",
      "fetched_at": "2026-01-28T18:51:29.513858"
    },
    {
      "id": "b7ceae5f553f",
      "title": "Egypte: Valu obtient une ligne de crédit de 64 millions de dollars auprès de la Banque nationale d'Égypte",
      "summary": "[Daba Finance] Valu a signé un accord de financement à court terme d'un montant maximal de 3 milliards EGP, soit l'équivalent d'environ 63,6 millions USD, avec la National Bank of Egypt, renforçant ainsi sa base de financement à mesure qu'elle se...",
      "link": "https://fr.allafrica.com/stories/202601280521.html",
      "source": "AllAfrica (FR)",
      "category": "Économie",
      "region": "Afrique du Nord",
      "published_at": "2026-01-28T16:02:54",
      "fetched_at": "2026-01-28T18:51:29.513897"
    },
    {
      "id": "4bf5eea7ed43",
      "title": "Egypte: La société NowPay s'implante en Arabie Saoudite dans le cadre d'une coentreprise de 20 millions de dollars",
      "summary": "[Daba Finance] NowPay se développe en Arabie Saoudite par le biais de NowAccess, une coentreprise avec Tas'heel, l'unité de crédit à la consommation de United International Holding Company.",
      "link": "https://fr.allafrica.com/stories/202601280522.html",
      "source": "AllAfrica (FR)",
      "category": "Économie",
      "region": "Afrique du Nord",
      "published_at": "2026-01-28T16:02:54",
      "fetched_at": "2026-01-28T18:51:29.513925"
    },
    {
      "id": "25cd2a53ea4b",
      "title": "Egypte: L'entreprise KNOT lève 1 million de dollars pour créer une plateforme de billetterie IA",
      "summary": "[Daba Finance] KNOT Technologies, une startup de billetterie en ligne basée en Égypte et au Royaume-Uni, a levé 1 million de dollars dans le cadre d'un tour de financement de pré-amorçage mené par A15.",
      "link": "https://fr.allafrica.com/stories/202601280519.html",
      "source": "AllAfrica (FR)",
      "category": "Économie",
      "region": "Afrique du Nord",
      "published_at": "2026-01-28T16:02:53",
      "fetched_at": "2026-01-28T18:51:29.513955"
    },
    {
      "id": "e73c963acc5d",
      "title": "Egypte: eYouth s'étend à l'Irak avec une plateforme de travail en arabe",
      "summary": "[Daba Finance] eYouth, l'entreprise d'apprentissage numérique fondée en Égypte, s'est implantée en Irak avec le lancement de eYouth Iraq, la première plateforme en ligne en langue arabe du pays axée sur le développement des compétences de la...",
      "link": "https://fr.allafrica.com/stories/202601280520.html",
      "source": "AllAfrica (FR)",
      "category": "Économie",
      "region": "Afrique du Nord",
      "published_at": "2026-01-28T16:02:53",
      "fetched_at": "2026-01-28T18:51:29.513986"
    },
    {
      "id": "247eb4ca9444",
      "title": "Kenya: Transport Lobby Warns of Nationwide Road Shutdown",
      "summary": "[Capital FM] Nairobi -- Transport operators have issued a warning of a nationwide road shutdown starting Monday, threatening massive disruption across major towns and highways as they protest what they describe as the government's failure to...",
      "link": "https://allafrica.com/stories/202601280499.html",
      "source": "AllAfrica",
      "category": "Économie",
      "region": "Afrique de l'Est",
      "published_at": "2026-01-28T14:42:01",
      "fetched_at": "2026-01-28T18:51:29.553315"
    },
    {
      "id": "82f87cf1ef00",
      "title": "Gambia: Judiciary Still Faces Shortage of Courtrooms &amp; Office Space",
      "summary": "[The Point] Chief Justice Hassan B. Jallow has highlighted the Judiciary's challenges, including shortage of courtrooms and office space, hindering judicial officers' effectiveness.",
      "link": "https://allafrica.com/stories/202601280497.html",
      "source": "AllAfrica",
      "category": "Économie",
      "region": "Afrique de l'Ouest",
      "published_at": "2026-01-28T14:41:25",
      "fetched_at": "2026-01-28T18:51:29.553526"
    },
    {
      "id": "c046de7e39a1",
      "title": "South Africa: Government Is Killing the Film Industry, Say Protesters",
      "summary": "[GroundUp] Hundreds of industry professionals marched in Cape Town calling for a meeting with trade and industry minister",
      "link": "https://allafrica.com/stories/202601280488.html",
      "source": "AllAfrica",
      "category": "Économie",
      "region": "Afrique Australe",
      "published_at": "2026-01-28T14:38:17",
      "fetched_at": "2026-01-28T18:51:29.553352"
    },
    {
      "id": "818449456023",
      "title": "Malawi: Malawi Budget Under Pressure",
      "summary": "[Nyasa Times] Malawi is tightening its belt under relentless fiscal pressure--yet beneath its soil lies an economic lifeline capable of transforming the nation's fortunes. With untapped mineral wealth estimated to generate over US$1.8 billion...",
      "link": "https://allafrica.com/stories/202601280483.html",
      "source": "AllAfrica",
      "category": "Économie",
      "region": "Afrique Australe",
      "published_at": "2026-01-28T14:34:51",
      "fetched_at": "2026-01-28T18:51:29.553388"
    },
    {
      "id": "25e77a19574c",
      "title": "East Africa: Why East Africa Tops Africa's 2026 Economic Projections",
      "summary": "[Independent (Kampala)] East Africa is expected to be Africa's fastest-growing subregion in 2026, with GDP projected to expand by 5.8%, according to the UN World Economic Situation and Prospects 2026. The UN names Ethiopia and Kenya as the main...",
      "link": "https://allafrica.com/stories/202601280383.html",
      "source": "AllAfrica",
      "category": "Économie",
      "region": "Afrique de l'Est",
      "published_at": "2026-01-28T12:25:48",
      "fetched_at": "2026-01-28T18:51:29.553554"
    },
    {
      "id": "21ab2d095441",
      "title": "Liberia: Konneh Says Boakai's Economic Gains Failed to Ease Hardship On Liberians",
      "summary": "[Liberian Investigator] MONROVIA -- Senator Amara M. Konneh on Wednesday issued a data-driven assessment of President Joseph Nyuma Boakai's third State of the Nation Address, warning that the administration's macroeconomic gains have yet to...",
      "link": "https://allafrica.com/stories/202601280359.html",
      "source": "AllAfrica",
      "category": "Économie",
      "region": "Afrique de l'Ouest",
      "published_at": "2026-01-28T12:05:38",
      "fetched_at": "2026-01-28T18:51:29.553578"
    },
    {
      "id": "47c14fa7f47e",
      "title": "Kenya: Doshi Joins Tabb Trade Credit Network to Expand SME Access to Stock Financing",
      "summary": "[Capital FM] Nairobi -- Leading hardware and electrical products supplier Doshi has joined tabb's trade credit network, enabling small and medium-sized enterprises (SMEs) to purchase inventory on extended, interest-free credit terms.",
      "link": "https://allafrica.com/stories/202601280265.html",
      "source": "AllAfrica",
      "category": "Commerce",
      "region": "Afrique de l'Est",
      "published_at": "2026-01-28T11:18:03",
      "fetched_at": "2026-01-28T18:51:29.546342"
    },
    {
      "id": "c2d4b72ec428",
      "title": "Laying rails to carry Africa’s economic ascent - Business Daily",
      "summary": "Laying rails to carry Africa’s economic ascent  Business Daily",
      "link": "https://news.google.com/rss/articles/CBMivgFBVV95cUxOQzd3R0hrTjhzSXV6UXIxeE9VNTdORmJqX0VXUS1EcF8teU1JSHI5a3BaNEtoMEM1bzdNbndpaTJjaHk3bnpReTFaZUdOZHZ1RzN3cHA4dUtyRTI0NzJQY3VhekJRMDAwZEJocmNBbHpucElVU3AxV09VTVQxLVRuVDZzMFRESTVKOHNWOEJFU0lLU1ZxQ3I1V2NyMUswZmEzNTRYckFEZGczc25nWkI2V18yWnRZbXFaeWJRU1BR?oc=5",
      "source": "Google News (Reuters, AFP, etc.)",
      "category": "Infrastructure",
      "region": "Afrique Centrale",
      "published_at": "2026-01-28T11:15:00",
      "fetched_at": "2026-01-28T18:51:29.991279"
    },
    {
      "id": "96b27bf2c5e4",
      "title": "Afrique: Le géant chinois Zijin Mining rachète plusieurs mines d'or au Mali, en Côte d'Ivoire et en Éthiopie",
      "summary": "[RFI] Le géant minier chinois Zijin Mining lance une offensive majeure sur l'or africain, avec le rachat de plusieurs mines au Mali, en Côte d'Ivoire et en Éthiopie pour près de 28 milliards de yuans. Cette opération intervient dans un contexte de...",
      "link": "https://fr.allafrica.com/stories/202601280249.html",
      "source": "AllAfrica (FR)",
      "category": "Économie",
      "region": "Afrique de l'Ouest",
      "published_at": "2026-01-28T10:54:42",
      "fetched_at": "2026-01-28T18:51:29.514022"
    },
    {
      "id": "b533f58da5af",
      "title": "L'Afrique au cœur des nouveaux équilibres économiques mondiaux - Anadolu Ajansı",
      "summary": "L'Afrique au cœur des nouveaux équilibres économiques mondiaux  Anadolu Ajansı",
      "link": "https://news.google.com/rss/articles/CBMiuAFBVV95cUxNUF9NUVV6eXlJRjZ3SzdUY1NscEI2SU1BdG96ZjI3UnRHaXFURFZOLUd1T1V6ZUY5c2NRY1U2dHlwbFhPc1g0bnY3bTh5QnpKVWFhcnp4OVN6dUJXa3pFTjZpVE5SeWdTTU90R2lOQkg1MEZJTFFLaTRIYlJlS2dEc2RXMzJrS2pvUDU4NEhZeDNHQi13UnhCQk05X3Z5NWRaWGt2SC1uazJMSE1aaHVibWlNcXpPVmxx?oc=5",
      "source": "Google News (Reuters, AFP, etc.)",
      "category": "Économie",
      "region": "Afrique",
      "published_at": "2026-01-28T09:53:33",
      "fetched_at": "2026-01-28T18:51:30.216944"
    },
    {
      "id": "6353e65c69af",
      "title": "Afrique: Revue de presse de l'Afrique francophone du 28 janvier 2026",
      "summary": "[allAfrica] iShowSpeed à la découverte de ses racines africaines lors d'une tournée sur le continent",
      "link": "https://fr.allafrica.com/stories/202601280161.html",
      "source": "AllAfrica (FR)",
      "category": "Économie",
      "region": "Afrique",
      "published_at": "2026-01-28T09:28:04",
      "fetched_at": "2026-01-28T18:51:29.513606"
    },
    {
      "id": "41dfec976844",
      "title": "Niger: Le Premier ministre Ali Mahamane Lamine Zeine perd le portefeuille des Finances",
      "summary": "[RFI] Au Niger, un léger réaménagement du gouvernement a été annoncé lundi 26 janvier 2026, sur décret d'Abdourahamane Tiani. Ali Mahamane Lamine Zeine perd le portefeuille de l'Économie et des finances, mais conserve la fonction de Premier ministre...",
      "link": "https://fr.allafrica.com/stories/202601280150.html",
      "source": "AllAfrica (FR)",
      "category": "Économie",
      "region": "Afrique de l'Ouest",
      "published_at": "2026-01-28T09:05:56",
      "fetched_at": "2026-01-28T18:51:29.513683"
    },
    {
      "id": "a57f951c3d13",
      "title": "Nigeria: We're Targeting $5bn Trade Volume With Nigeria - President Erdogan",
      "summary": "[Vanguard] President Recep Tayyip Erdogan of the Republic of Turkiye, in Ankara on Tuesday, reaffirmed his country's commitment to a $5 billion trade volume target with Nigeria.",
      "link": "https://allafrica.com/stories/202601280136.html",
      "source": "AllAfrica",
      "category": "Commerce",
      "region": "Afrique de l'Ouest",
      "published_at": "2026-01-28T08:51:50",
      "fetched_at": "2026-01-28T18:51:29.546366"
    },
    {
      "id": "3502aea81e52",
      "title": "Nigeria: World Bank Offers $250bn Procurement Window to Nigerian Firms",
      "summary": "[Vanguard] The World Bank has offered a $250 billion global procurement window to Nigerian firms, urging local companies to take advantage of thousands of opportunities across World Bank-financed projects worldwide.",
      "link": "https://allafrica.com/stories/202601280118.html",
      "source": "AllAfrica",
      "category": "Finance",
      "region": "Afrique de l'Ouest",
      "published_at": "2026-01-28T08:19:48",
      "fetched_at": "2026-01-28T18:51:29.569154"
    },
    {
      "id": "8a5d9137a530",
      "title": "African Business Chamber (AfBC) intelligence brief: Africa economic and market growth outlook 2026 – Virtual webinar - CLUB OF MOZAMBIQUE",
      "summary": "African Business Chamber (AfBC) intelligence brief: Africa economic and market growth outlook 2026 – Virtual webinar  CLUB OF MOZAMBIQUE",
      "link": "https://news.google.com/rss/articles/CBMi4wFBVV95cUxOWXJKbkU4cHNZa1FGRlRjMHJHT0FfZl9abTd2XzR4OHhCa3pnaEhkdVhBUWFKUGtUN3k5SXlsZk9rTUV1ZmZ2bmZ2ODhjUHNvZFlkaFIwMS1fMlRuVXlHUTRoR1ZSTU1BN3B5OF9HRVBHUmY0Y1M2LWpCa3E5ZDBMYVR0aS1feVVyaldzQ3FtQ3dDcmNidVRrT3Fqenc0UElfRi0tYUVuS2tMSUM2NHl6ZWJZMmd6WWRCcWNfQ1dTREhJdlJPOGRaa1FORWhxRENVclh4WFZaX2J2M3hUOXFwZkNtdw?oc=5",
      "source": "Google News (Reuters, AFP, etc.)",
      "category": "Économie",
      "region": "Afrique Australe",
      "published_at": "2026-01-28T08:02:39",
      "fetched_at": "2026-01-28T18:51:29.991062"
    },
    {
      "id": "16d7b4b40065",
      "title": "Tanzania to sell gold reserves to finance infrastructure projects - Business Insider Africa",
      "summary": "Tanzania to sell gold reserves to finance infrastructure projects  Business Insider Africa",
      "link": "https://news.google.com/rss/articles/CBMivwFBVV95cUxPUDNVMUtqVVUyT3ZBa056Sk9NQndGak5CZ2FHbk5jTDdSNlluRnFaYkdGOUV4XzZ2TFgwSkRXdFFHV3NzOGRCVXJsQnNsXzA2ekhMeGg3eVZTYUxNMEpQZ3lsQ1lYSy1iQXhSWDdrcnhpZTJCcEFOS29naUhHbUxkeDA0YWppeC1oLVJVVUdOZ1YxeGstR09HTEQ4a0t3VjljLVYzV0hSRko0M2c0ODgwSm1Ucy10bmZjdE83TzBPTQ?oc=5",
      "source": "Google News (Reuters, AFP, etc.)",
      "category": "Finance",
      "region": "Afrique de l'Est",
      "published_at": "2026-01-28T07:52:10",
      "fetched_at": "2026-01-28T18:51:29.990988"
    },
    {
      "id": "1710e1d44dd8",
      "title": "Nigeria: Nigeria, Turkiye Sign Nine Agreements, Target $5 Billion Trade Volume",
      "summary": "[Premium Times] Mr Erdogan said the establishment of the Joint Economy and Trade Committee between the two countries will create opportunities to expand Turkish investments in Nigeria.",
      "link": "https://allafrica.com/stories/202601280108.html",
      "source": "AllAfrica",
      "category": "Commerce",
      "region": "Afrique de l'Ouest",
      "published_at": "2026-01-28T07:23:17",
      "fetched_at": "2026-01-28T18:51:29.546287"
    },
    {
      "id": "0911f24901b4",
      "title": "Africa: All of Africa Today - January 28, 2025",
      "summary": "[allAfrica]",
      "link": "https://allafrica.com/stories/202601280107.html",
      "source": "AllAfrica",
      "category": "Économie",
      "region": "Afrique",
      "published_at": "2026-01-28T07:22:10",
      "fetched_at": "2026-01-28T18:51:29.553423"
    },
    {
      "id": "c4a3c7132a27",
      "title": "Government-Business Partnership enters Phase Three - South African Government News Agency",
      "summary": "Government-Business Partnership enters Phase Three  South African Government News Agency",
      "link": "https://news.google.com/rss/articles/CBMikwFBVV95cUxQOWFBUG1NcUZRVFA5ME0yc29SRnk0bjNKUmVRaFdjVUI3REJPT3Q0QUxVbXM3QmlTN1N2UTRUb1l4VEtUclhvbFFaVXV5QU5UaFN3bVU0eGNYcERYU1FZckYzazQ4WXhPVkxQY08wLUh2MUltUUxSSGZZbmF6cWlybG1Oc0x0MHZMRno5b3NWYWJzUDg?oc=5",
      "source": "Google News (Reuters, AFP, etc.)",
      "category": "Économie",
      "region": "Afrique Australe",
      "published_at": "2026-01-28T06:42:34",
      "fetched_at": "2026-01-28T18:51:29.991394"
    },
    {
      "id": "bb9f58ff7c11",
      "title": "Nigeria: CBN Grants Two-Month Grace Period On Expired NAFDAC Licences for Form M",
      "summary": "[This Day] The Central Bank of Nigeria (CBN) has approved a two-month temporary dispensation allowing the continued use of NAFDAC licences that expired on December 31, 2025, for the processing of Forms M.",
      "link": "https://allafrica.com/stories/202601280093.html",
      "source": "AllAfrica",
      "category": "Finance",
      "region": "Afrique de l'Ouest",
      "published_at": "2026-01-28T06:40:15",
      "fetched_at": "2026-01-28T18:51:29.569186"
    },
    {
      "id": "da93e1407141",
      "title": "Nigeria: Turkiye Targeting $5bn in Trade With Nigeria, Also to Help in Fighting Terrorism - Erdogan",
      "summary": "[This Day] President of the Republic of Turkiye, Recep Tayyip Erdogan, has disclosed his country's commitment to a $5 billion trade volume target with Nigeria, even as he hinted at his country's resolve to help Nigeria fight insecurity.",
      "link": "https://allafrica.com/stories/202601280091.html",
      "source": "AllAfrica",
      "category": "Commerce",
      "region": "Afrique de l'Ouest",
      "published_at": "2026-01-28T06:40:14",
      "fetched_at": "2026-01-28T18:51:29.546312"
    },
    {
      "id": "554c8bc4595c",
      "title": "Nigeria: World Bank Committed $2.5 Billion Into Nigeria's Infrastructure, Education, Healthcare Sectors in 5 Years",
      "summary": "[This Day] The World Bank Group said it has committed over $2.5 billion to Nigerian suppliers over the past five years, funding projects across infrastructure, healthcare, and education.",
      "link": "https://allafrica.com/stories/202601280092.html",
      "source": "AllAfrica",
      "category": "Finance",
      "region": "Afrique de l'Ouest",
      "published_at": "2026-01-28T06:40:14",
      "fetched_at": "2026-01-28T18:51:29.569210"
    },
    {
      "id": "4bc1c97c5209",
      "title": "Afrique économie - Guinée: orpailleur artisanal, une profession à haut risque - RFI",
      "summary": "Afrique économie - Guinée: orpailleur artisanal, une profession à haut risque  RFI",
      "link": "https://news.google.com/rss/articles/CBMixwFBVV95cUxPdDFUZ0JuaTNYeXRUR0Y5bE9mdi1iMzZNSTZMbU1QMEI5SWVKTlZVblNyS2toYWVwaVZ5UkhfSklFMlVpdnZYbEMxQjl0cnVlTV9IMU0wV0xBRVdjdFJKT2xMMjJObFR2SHJqVW9xdy1aSDA2SUMtdXB2TmdnV0Rka0hSdDBHUEtBS29yM09mczQ2aGEtREdpVUVFNFZ1b1BBY2h4R3pPdFZ1bWVTTUdvSHRiRHVRMVIxb05RTVJGQVI4MVdMVHpR?oc=5",
      "source": "Google News (Reuters, AFP, etc.)",
      "category": "Mines",
      "region": "Afrique de l'Ouest",
      "published_at": "2026-01-27T23:11:00",
      "fetched_at": "2026-01-28T18:51:30.216890"
    },
    {
      "id": "b3e0f708849d",
      "title": "Namibia: Nespresso Sets Up Shop in Windhoek",
      "summary": "[Namibian] Well-known coffee brand Nespresso opened its first Namibian nano boutique at the Grove Mall in Windhoek on Friday.",
      "link": "https://allafrica.com/stories/202601270742.html",
      "source": "AllAfrica",
      "category": "Commerce",
      "region": "Afrique Australe",
      "published_at": "2026-01-27T22:15:15",
      "fetched_at": "2026-01-28T18:51:29.546458"
    },
    {
      "id": "2861ff976295",
      "title": "Rwanda: Plasma Exports Set to Start By Year-End, Says RBC",
      "summary": "[New Times] Rwanda is expected to start exporting blood plasma for fractionation later this year, once the remaining technical and regulatory requirements are completed, according to Dr Thomas Muyombo, Blood Transfusion Division Manager at Rwanda...",
      "link": "https://allafrica.com/stories/202601270720.html",
      "source": "AllAfrica",
      "category": "Commerce",
      "region": "Afrique de l'Est",
      "published_at": "2026-01-27T20:23:12",
      "fetched_at": "2026-01-28T18:51:29.546487"
    },
    {
      "id": "f3c050026a41",
      "title": "Malawi: Old Mutual Rewards Top Performers With International Trips",
      "summary": "[Nyasa Times] Old Mutual Malawi has rewarded 20 of its top-performing employees with international incentive trips to Malaysia and Durban, South Africa, in recognition of their outstanding performance in 2025.",
      "link": "https://allafrica.com/stories/202601270715.html",
      "source": "AllAfrica",
      "category": "Finance",
      "region": "Afrique Australe",
      "published_at": "2026-01-27T20:17:23",
      "fetched_at": "2026-01-28T18:51:29.569367"
    },
    {
      "id": "514225af7926",
      "title": "Sudan: Khartoum Bank Plan to Finance the Cultivation of 100,000 Acres in Al-Gezira",
      "summary": "[SNA] - Wali of Al-Gezira State Al-Tahir Ibrahim Al-Khair welcomed on Monday a delegation from Khartoum Bank, headed by the Bank's General Manager Limya Kamal Satti, during a meeting at his office.",
      "link": "https://allafrica.com/stories/202601270706.html",
      "source": "AllAfrica",
      "category": "Finance",
      "region": "Afrique de l'Est",
      "published_at": "2026-01-27T19:15:25",
      "fetched_at": "2026-01-28T18:51:29.569396"
    },
    {
      "id": "b5bb89e78397",
      "title": "Nigeria: Paypal Returns to Nigeria Through Paga After Two Decades",
      "summary": "[Daba Finance] PayPal is partnering with Nigerian fintech Paga to allow Nigerians receive international payments, settle funds in naira, and access PayPal's global network after nearly 20 years of restricted service.",
      "link": "https://allafrica.com/stories/202601270689.html",
      "source": "AllAfrica",
      "category": "Finance",
      "region": "Afrique de l'Ouest",
      "published_at": "2026-01-27T17:39:39",
      "fetched_at": "2026-01-28T18:51:29.569232"
    },
    {
      "id": "e77c7d362815",
      "title": "Saudi Arabia’s $400 Billion Investment Surge Signals New Era for Africa–Gulf Economic Partnership - The Voice of Africa",
      "summary": "Saudi Arabia’s $400 Billion Investment Surge Signals New Era for Africa–Gulf Economic Partnership  The Voice of Africa",
      "link": "https://news.google.com/rss/articles/CBMi0gFBVV95cUxPT3Vxa084NldiNkdtejJ0YkZjZ0pGTHBLU25XVVN2ak9QVmUtVUpqWGxteU5rUDR6MF9GQ0p0aEhJZG13dEo2NGlRNmloVnpjQ1EtVGw0TEZGZVhzRDE0YllzVkZ3ZlpRRk9TbkF0aGZOWjU0YmtWdHdPaUt5NFRoOUlSTW1MTmhUV2ZNUU1jekExdEVMTmx4Ykp3TVhVemFIZHBfM1JDd0pXV0dFMGplMm1NMzJWM0k0ZHBwVzQ1M0xFYWVhcWs5REsxWC1XdzFhNkE?oc=5",
      "source": "Google News (Reuters, AFP, etc.)",
      "category": "Finance",
      "region": "Afrique",
      "published_at": "2026-01-27T09:54:56",
      "fetched_at": "2026-01-28T18:51:29.991243"
    },
    {
      "id": "a7ef3456bddf",
      "title": "Nigeria: CBN Upgrades Opay, Moniepoint, Palmpay, Others to National Licenses",
      "summary": "[Vanguard] The Central Bank of Nigeria (CBN) has upgraded the licenses of major FinTech companies and Microfinance Banks, including Opay and Moniepoint, to national status, allowing them to operate across the country following compliance with...",
      "link": "https://allafrica.com/stories/202601270102.html",
      "source": "AllAfrica",
      "category": "Finance",
      "region": "Afrique de l'Ouest",
      "published_at": "2026-01-27T06:56:09",
      "fetched_at": "2026-01-28T18:51:29.569255"
    },
    {
      "id": "ecc752d040f8",
      "title": "Somalia: Oketch Salah Holds Consultative Meeting With Puntland President On Trade and Regional Cooperation",
      "summary": "[Capital FM] Nairobi -- Oketch Salah on Monday met with President Said Abdullahi Deni of Puntland, Somalia, in a consultative session focused on strengthening trade ties between the two regions.",
      "link": "https://allafrica.com/stories/202601270043.html",
      "source": "AllAfrica",
      "category": "Commerce",
      "region": "Afrique de l'Ouest",
      "published_at": "2026-01-27T05:09:31",
      "fetched_at": "2026-01-28T18:51:29.546388"
    },
    {
      "id": "e11d561db20e",
      "title": "Mozambique: New Country Partnership Framework With World Bank",
      "summary": "[AIM] Maputo -- The World Bank Board of Executive on Thursday endorsed a new Country Partnership Framework (CPF) fpr the period 2026 to 2031.",
      "link": "https://allafrica.com/stories/202601270022.html",
      "source": "AllAfrica",
      "category": "Finance",
      "region": "Afrique Australe",
      "published_at": "2026-01-27T05:05:52",
      "fetched_at": "2026-01-28T18:51:29.569306"
    },
    {
      "id": "43e9ef565de5",
      "title": "Nigeria: Weak Data, Poor Pay Stalling $500m World Bank-Funded Metering Scheme",
      "summary": "[This Day] Poor remuneration for installers and lack of clean data of unmetered customers of Distribution Companies (Discos) is the main cause of the slow pace of deployment of the World Bank-funded smart electricity meters under the Distribution...",
      "link": "https://allafrica.com/stories/202601270014.html",
      "source": "AllAfrica",
      "category": "Finance",
      "region": "Afrique de l'Ouest",
      "published_at": "2026-01-27T04:51:45",
      "fetched_at": "2026-01-28T18:51:29.569277"
    },
    {
      "id": "cadeda457f41",
      "title": "Afrique économie - En Tunisie, les agricultrices à la conquête de la propriété et des marchés - RFI",
      "summary": "Afrique économie - En Tunisie, les agricultrices à la conquête de la propriété et des marchés  RFI",
      "link": "https://news.google.com/rss/articles/CBMi8gFBVV95cUxQcVU4V1B5c081NlIyMi1PMGtLMU5VV19IYlkzYkNwZkJwTzVGTnRSRTk5OUh1ZFBHdEs0bEpvaXNLdFdkUWIwaHdBamVlMk1wRHlBVTJublZHbXA4M3ZiUERZeVBCNFd1WHNfWGtJY01vamp4a1g5Y0Z6MGk1SE9KcXM4ZklQM2xianp6X1gzLXY4UHNtcW1iSnU5S1FtU0FRdmU1cmNWNmdabmRqbUpCSHRHSjBHVFV3UTM3c3k2aFNJQWtZbjVRV0VqdTV0SlR4dk1LZUtjSVo5b2NlbHJWX1k0eW9JYzdFYjBQZkhqdXBpQQ?oc=5",
      "source": "Google News (Reuters, AFP, etc.)",
      "category": "Économie",
      "region": "Afrique du Nord",
      "published_at": "2026-01-26T23:03:00",
      "fetched_at": "2026-01-28T18:51:30.217073"
    },
    {
      "id": "f895e7d5d32c",
      "title": "Ethiopia: CBE Says Digital Platforms Handled Over Nine Trillion Birr, Accounting for 87 Percent of Half-Year Transactions",
      "summary": "[Addis Standard] Addis Abeba -- The Commercial Bank of Ethiopia (CBE) says transactions conducted through its digital banking platforms surpassed nine trillion birr in the first half of the 2025/26 fiscal year, accounting for nearly 88 percent of...",
      "link": "https://allafrica.com/stories/202601260528.html",
      "source": "AllAfrica",
      "category": "Finance",
      "region": "Afrique de l'Est",
      "published_at": "2026-01-26T15:10:40",
      "fetched_at": "2026-01-28T18:51:29.569336"
    },
    {
      "id": "0be76647d3c7",
      "title": "Somalia: Somalia, China Discuss Boosting Trade and Economic Cooperation",
      "summary": "[Shabelle] Mogadishu -- Somalia's Minister of Commerce and Industry, Gamal Mohamed Hassan met with China's ambassador to Somalia, Wang Yu, to discuss ways to strengthen bilateral cooperation in trade, investment and economic development, the...",
      "link": "https://allafrica.com/stories/202601260508.html",
      "source": "AllAfrica",
      "category": "Commerce",
      "region": "Afrique de l'Ouest",
      "published_at": "2026-01-26T14:56:33",
      "fetched_at": "2026-01-28T18:51:29.546410"
    },
    {
      "id": "368f7c72b207",
      "title": "Kenya: Kenya, Rwanda Formalise KPA Kigali Office to Strengthen Regional Trade",
      "summary": "[New Times] For more than 12 years, the Port of Mombasa has served the Rwandan market, positioning itself as the region's most modern and efficient gateway for international trade.",
      "link": "https://allafrica.com/stories/202601260098.html",
      "source": "AllAfrica",
      "category": "Commerce",
      "region": "Afrique de l'Ouest",
      "published_at": "2026-01-26T08:05:14",
      "fetched_at": "2026-01-28T18:51:29.546431"
    },
    {
      "id": "2f15d13a95e7",
      "title": "Afrique du Sud : le Sommet de l’économie verte d’Afrique 2026 se tiendra en février - We are Tech",
      "summary": "Afrique du Sud : le Sommet de l’économie verte d’Afrique 2026 se tiendra en février  We are Tech",
      "link": "https://news.google.com/rss/articles/CBMi0gFBVV95cUxNQV9KTFlWZUxUWlZONDlTN1QxRkNtX1dJa1ZsRHBUOGQtUFVQVWFqQUVjeXduNTdfUlhmVDBGNUdCdmhTUXBWcVoyT2NjdXhDY0lKampaRnlsLVNqUmRIWW83a29YT1dnczRwOGROYmtLUk1aVjRPNUFFYUpidmpsQTlueTlycDRLMm1hWWFDOGVKZHJ1SERTaS1NT3dTNjgwdlNPa3dKWU9oeTdKOFhRd2NjSi1uaE96ZFJ5TjJsQkZtbEhOOFZrQno5NW9uTUc1UEE?oc=5",
      "source": "Google News (Reuters, AFP, etc.)",
      "category": "Télécoms",
      "region": "Afrique Australe",
      "published_at": "2026-01-26T07:50:00",
      "fetched_at": "2026-01-28T18:51:30.216993"
    },
    {
      "id": "1948fa3be09b",
      "title": "Afrique économie - Infrastructures, tourisme, investissements: une CAN 2025 gagnante pour le Maroc - RFI",
      "summary": "Afrique économie - Infrastructures, tourisme, investissements: une CAN 2025 gagnante pour le Maroc  RFI",
      "link": "https://news.google.com/rss/articles/CBMi1AFBVV95cUxQaVpPWmVWWTdKWmhiUFRMMGNjWG9NU2tMWGxLcUg4UHlSTnc0WmNoTHRFMVBOTDU0RG1ieTZIdzI0YlFmRzlGYWYtejJBcXczemNSYWhDOGhzd3lEb0p6bUllR3dKTERZZUVyWjdsa1dJbndoSXQtZkZDTnMxZHNuZU53c2c4T004dkwxakhXVnplZDNEekFFRl81VEo1YXc3SWp2bFV2T25hcXBSZWVkRllBS0pvZWh1aG9BVHAxV3ZkemdzQ1Zsc09XQzRWME9OQ2xENA?oc=5",
      "source": "Google News (Reuters, AFP, etc.)",
      "category": "Finance",
      "region": "Afrique du Nord",
      "published_at": "2026-01-22T23:00:00",
      "fetched_at": "2026-01-28T18:51:30.217181"
    },
    {
      "id": "82b1c62532a7",
      "title": "Adaptation au changement climatique en Afrique : comprendre, planifier, investir - AFD - Agence Française de Développement",
      "summary": "Adaptation au changement climatique en Afrique : comprendre, planifier, investir  AFD - Agence Française de Développement",
      "link": "https://news.google.com/rss/articles/CBMirgFBVV95cUxOd2o4cXYwMFRHaTVPc2RqY1BNb2VCV0hhb0VwS3dzZW5jdVppWk1jMUpJRmtzdDFySHdHUlZTVzFXckgzT2dMaXE1NlNtQ1MtYW5uUmNNVnlwS09Yd3Y4am9HSkZFM09kTHNMSmhHMFM2QjN3TE8wd3J5YnloWDZseGhXMTM3NTlDdjIwWlI0OGtnSmNkcTE1eEplNTRqRVBxeHMxY255WTNqdG1EU1E?oc=5",
      "source": "Google News (Reuters, AFP, etc.)",
      "category": "Économie",
      "region": "Afrique",
      "published_at": "2026-01-22T12:00:00",
      "fetched_at": "2026-01-28T18:51:30.216840"
    },
    {
      "id": "9abf978cbc7e",
      "title": "Afrique économie - Infrastructures, commerce, emploi: l’Afrique mise sur les corridors intégrés - RFI",
      "summary": "Afrique économie - Infrastructures, commerce, emploi: l’Afrique mise sur les corridors intégrés  RFI",
      "link": "https://news.google.com/rss/articles/CBMi3gFBVV95cUxQTG9Mb3RLVTJlcjdpNk85bW9vVFBiUkd0anpsRXFKc2JlNHg2TkpjZm0wQkpIMHZxSTZFejVDU05EMFN0UGtoUmVsTDRDbDJaa3FGRTdUM3JDTUJUcWxJelJ5RUltcWtQNHppMXFPRXVBVE0yNC1pSDBSemsxTjc2U2pzRUhybnhHWlZEVmkwRnMtd1NOaFp0U0J2OGpPd0MtblctS3lyVzFaTk9OLS1DMjV0eVNTUkg3MjhJNDgwVkZMOVZHUENhcUtEbTBpTVB6UnRVdU1ZTFhDMDh6U2c?oc=5",
      "source": "Google News (Reuters, AFP, etc.)",
      "category": "Commerce",
      "region": "Afrique",
      "published_at": "2026-01-20T23:00:00",
      "fetched_at": "2026-01-28T18:51:30.217220"
    },
    {
      "id": "b2511c300d77",
      "title": "Unlocking Africa’s economic potential through innovative financing - African Business",
      "summary": "Unlocking Africa’s economic potential through innovative financing  African Business",
      "link": "https://news.google.com/rss/articles/CBMitAFBVV95cUxPejFST2tlQ0hpcVQyWlJ3R2hPLVB4R1J5aFkzSnRPeUx2QU1JdGV1aU5BV3ZibUFEVGdYN1BqV0lrZDlURXFqOG42c1ZoLWFEYkNBRFAyYnlQejM2Zlg0ZEtJODNlZ1l3bmFVc2psc25GWEk0alNtVTFNY2dfVU52bjdfaGVOaHEyOHVRZElTbFBRa040WFRKTGtXRDNQZ3NMeVAyYnlCVzVjeldSYWdneWk2Qk0?oc=5",
      "source": "Google News (Reuters, AFP, etc.)",
      "category": "Économie",
      "region": "Afrique",
      "published_at": "2026-01-07T08:00:00",
      "fetched_at": "2026-01-28T18:51:29.991163"
    },
    {
      "id": "8b7debcd3fa4",
      "title": "Africa's economy to expand in 2026 despite risks [Business Africa] - africanews.com",
      "summary": "Africa's economy to expand in 2026 despite risks [Business Africa]  africanews.com",
      "link": "https://news.google.com/rss/articles/CBMipAFBVV95cUxPMTFOY01FQ1NaMXNqNjlGVUFHUG8tZjREUk5zeGUyNDlRcEJwWHdQQThjSmtFeU5rXzhVOXdEYWxQN0ZKb1BqeTBWeTJMUGY1c1IxbWlGWGdtNEs1Q1lNVHN2cWRqLXVBZGxoTllMM2M4TlpzVTFDdS1WV1BSM1d0M243dGNGOVI5NTg5TzhnRi1FNDZPZmlnSW1JdzBYb1c3dGMwWdIBqgFBVV95cUxPWk04N2U5U0RTajNESmlxcGdGT1FEWFFwdkRBQy1CZTFBRkQwa2JiSTE0dWZubjBZdVJsV3JhRG50OVpXTTlCVHZVVnhiRzk1dEVEUVZJckhZWExmMkR0cWV2a3otMHlGSFdXTzRpMGRiVW4zN3VnWDRnZTBmR3lWNElKRGw0bGpPNGtIXzVERm93eHowQ3psUnFMZUcwVWY1YWhJQ2F0MDBrQQ?oc=5",
      "source": "Google News (Reuters, AFP, etc.)",
      "category": "Économie",
      "region": "Afrique",
      "published_at": "2026-01-02T08:00:00",
      "fetched_at": "2026-01-28T18:51:29.991111"
    },
    {
      "id": "00333340ded0",
      "title": "L'économie africaine devrait connaître une expansion en 2026 [Business Africa] - Africanews",
      "summary": "L'économie africaine devrait connaître une expansion en 2026 [Business Africa]  Africanews",
      "link": "https://news.google.com/rss/articles/CBMiswFBVV95cUxNSVVUaWZvRXR3V093LWhMbFJNU1ZPMmZ6Smx5cDBQeFphdHRUTW5tVGQyNkNnTDM3b2lSOHhtb3Q1bG5YZ09tSk50V3pFMHRmNnpYWGh6bUxmQ2pMMmFJY2FIYTJVMlNER1p1anhWQU9RVEpORWpHYnR4aFlhMmtNSDRDVEI1T0pUOGJoZS1mNXh4bFA3N3ppSDVvSXUyaHBod09LaUNuNGdLcDIxYzNldDZvMNIBuAFBVV95cUxOUHByWWphYmpzb1dXUVVtSzVYNm01eGVtZXQ3d01aY3I5R0tqa2lBR25TVXhaT1J1LWRKQzVyZXhrNG8yNnVHR0RhVlFpMGZEQ0lLOEhqRlJmZlNHNjdnM0dKcktmZDEwaVNoUERFZDVHT1FTMVFOcEVnYUNKdHhlWThxMkJ4THFhaE9SVjVaVHVmcWpOMGV3UlNwRGpzSjFFbDJHcXVaRDJnVUxKT0hDUmFvLTl5a1pK?oc=5",
      "source": "Google News (Reuters, AFP, etc.)",
      "category": "Économie",
      "region": "Afrique",
      "published_at": "2026-01-02T08:00:00",
      "fetched_at": "2026-01-28T18:51:30.217120"
    },
    {
      "id": "884bcb9ac12d",
      "title": "Afrique - AFD - Agence Française de Développement",
      "summary": "Afrique  AFD - Agence Française de Développement",
      "link": "https://news.google.com/rss/articles/CBMiVEFVX3lxTE9nUDVSRDNWVnJoeXMtZGM2dk9vazFxdEMtMDBTeHNQQWVIZGhQcHU4aEF3NDhhTTB2NXJ5NkxyZHAzMFhhVjJZcUNabm1SR1NCRXhxSA?oc=5",
      "source": "Google News (Reuters, AFP, etc.)",
      "category": "Économie",
      "region": "Afrique",
      "published_at": "2025-12-08T22:15:09",
      "fetched_at": "2026-01-28T18:51:30.217156"
    },
    {
      "id": "76ec584e5134",
      "title": "Afrique : 108 milliards USD de gap financier à combler - Africa24 TV",
      "summary": "Afrique : 108 milliards USD de gap financier à combler  Africa24 TV",
      "link": "https://news.google.com/rss/articles/CBMigAFBVV95cUxPT3E2Z3BJanVyMjJaRzg1S3VsLXQyTncwVXg4MnZia1Vna3prTVBNYnZCc1BEZmo4aTUxR3NHNWlYYkNOWlVZd2ZXU0ZvSkhfczY5RVJtQ3c0ZXdrekFhQW9seU9hcVl4VGJ5OGxFTUktNkNPNFFUUTUxZmVyMWJreA?oc=5",
      "source": "Google News (Reuters, AFP, etc.)",
      "category": "Économie",
      "region": "Afrique",
      "published_at": "2025-11-05T08:00:00",
      "fetched_at": "2026-01-28T18:51:30.217037"
    },
    {
      "id": "514a5a16a5b1",
      "title": "South African business confidence edges up in July ahead of Trump's 30% tariff - Reuters",
      "summary": "South African business confidence edges up in July ahead of Trump's 30% tariff  Reuters",
      "link": "https://news.google.com/rss/articles/CBMiuwFBVV95cUxPMDl4ekN3dlBJUzJHdTZpMzlLYVhWcnVJY1IzclVJc1BabWNSMnVkLWhOQUU5dlNDTFQ5VGw2d0FNMnJOQjItdWU3bGpjX25kMzBDb29rNUtZeVVNcHpEWV91bFRrNGk0NllzamFXZ3VGX0xzM2hVS0IxekhWQ3p4ZjFHUUpweVk4ZHRoclpzX1Z6QUpLakNfXzkzczNJZEFUeXRhb01FTVFQOWR3V0ozb1FoQXRYNzF6SGcw?oc=5",
      "source": "Google News (Reuters, AFP, etc.)",
      "category": "Commerce",
      "region": "Afrique Australe",
      "published_at": "2025-08-13T07:00:00",
      "fetched_at": "2026-01-28T18:51:29.991313"
    },
    {
      "id": "da0af33c4a49",
      "title": "Strengthening U.S.-Africa Economic Ties at the Highest Level - U.S. Chamber of Commerce",
      "summary": "Strengthening U.S.-Africa Economic Ties at the Highest Level  U.S. Chamber of Commerce",
      "link": "https://news.google.com/rss/articles/CBMihgFBVV95cUxNWnRBUUNJRTFPdUppMlJOdkU2eWptdDZRQ3NFRzNWTkhtd0xURmV2WThYaWxPczZLX1pDUFhWREgxdDZ5cWVYeUF4THZvM0gybHp6WG1uZloyZW4yNVJPNHo5VmtrcUJFLWJGWExvR1lfeDlfdjFhVE9mOVVkVG1fdnZHUlNkQQ?oc=5",
      "source": "Google News (Reuters, AFP, etc.)",
      "category": "Commerce",
      "region": "Afrique",
      "published_at": "2025-07-23T07:00:00",
      "fetched_at": "2026-01-28T18:51:29.991200"
    }
  ]
}